bayne/__init__.py
bayne/mcmc.py
bayne/util.py
bayne-0.2.2.dist-info/LICENSE
bayne-0.2.2.dist-info/METADATA
bayne-0.2.2.dist-info/WHEEL
bayne-0.2.2.dist-info/top_level.txt
bayne-0.2.2.dist-info/RECORD
